sunset_repos/__init__.py
sunset_repos/archive.py
sunset_repos/cli.py
sunset_repos-1.0.1.dist-info/LICENSE.txt
sunset_repos-1.0.1.dist-info/METADATA
sunset_repos-1.0.1.dist-info/WHEEL
sunset_repos-1.0.1.dist-info/entry_points.txt
sunset_repos-1.0.1.dist-info/top_level.txt
sunset_repos-1.0.1.dist-info/RECORD
