Metadata-Version: 2.1
Name: sunset-repos
Version: 1.0.1
Summary: Archive batches of GitHub repositories
Home-page: https://github.com/deriksson/sunset-repos
Author: Daniel Eriksson
Author-email: gustaf.daniel.eriksson@gmail.com
License: UNKNOWN
Platform: UNKNOWN
Classifier: Programming Language :: Python :: 3
Classifier: License :: OSI Approved :: MIT License
Classifier: Operating System :: OS Independent
Requires-Python: >=3.6
Requires-Dist: Click (>=7.0)
Requires-Dist: requests (>=2.22.0)
